pDESy/__init__.py
pDESy/model/__init__.py
pDESy/model/base_component.py
pDESy/model/base_facility.py
pDESy/model/base_priority_rule.py
pDESy/model/base_product.py
pDESy/model/base_project.py
pDESy/model/base_subproject_task.py
pDESy/model/base_task.py
pDESy/model/base_team.py
pDESy/model/base_worker.py
pDESy/model/base_workflow.py
pDESy/model/base_workplace.py
pdesy-0.7.4.dist-info/METADATA
pdesy-0.7.4.dist-info/WHEEL
pdesy-0.7.4.dist-info/licenses/LICENSE
pdesy-0.7.4.dist-info/RECORD
