Metadata-Version: 2.4
Name: pdesy
Version: 0.7.4
Summary: pDESy: Discrete Event Simulation of Python
License: MIT
License-File: LICENSE
Author: Taiga MITSUYUKI
Author-email: mitsuyuki-taiga-my@ynu.ac.jp
Requires-Python: >=3.11
Classifier: License :: OSI Approved :: MIT License
Classifier: Programming Language :: Python :: 3
Classifier: Programming Language :: Python :: 3.11
Classifier: Programming Language :: Python :: 3.12
Classifier: Programming Language :: Python :: 3.13
Classifier: Programming Language :: Python :: 3.14
Requires-Dist: ipykernel (>=6.29.5,<7.0.0)
Requires-Dist: kaleido (==0.2.1)
Requires-Dist: matplotlib (>=3.10.1,<4.0.0)
Requires-Dist: nbformat (>=5.10.4,<6.0.0)
Requires-Dist: networkx (>=3.4.2,<4.0.0)
Requires-Dist: numpy (>=2.2.4,<3.0.0)
Requires-Dist: pandas (>=2.3.3,<3.0.0)
Requires-Dist: plotly (>=6.0.1,<7.0.0)
Requires-Dist: tqdm (>=4.67.1,<5.0.0)
